[{"addr":"0x6dbfb0","name":"sub_6DBFB0","size":"0xad","has_type":false},{"addr":"0x6dc060","name":"sub_6DC060","size":"0x1d","has_type":false},{"addr":"0x6dc080","name":"sub_6DC080","size":"0x56","has_type":false},{"addr":"0x6dc140","name":"sub_6DC140","size":"0xf6","has_type":false},{"addr":"0x6dc270","name":"sub_6DC270","size":"0x12f","has_type":false},{"addr":"0x6dc3c0","name":"sub_6DC3C0","size":"0x6b","has_type":false},{"addr":"0x6dc430","name":"sub_6DC430","size":"0x6b","has_type":false},{"addr":"0x6dc4d0","name":"sub_6DC4D0","size":"0x79","has_type":false},{"addr":"0x6dc580","name":"sub_6DC580","size":"0xb3","has_type":false},{"addr":"0x6dc640","name":"sub_6DC640","size":"0x51","has_type":false},{"addr":"0x6dc6a0","name":"sub_6DC6A0","size":"0x53","has_type":false},{"addr":"0x6dc700","name":"sub_6DC700","size":"0x6d","has_type":false},{"addr":"0x6dc770","name":"sub_6DC770","size":"0x6d","has_type":false},{"addr":"0x6dc800","name":"sub_6DC800","size":"0x7d","has_type":false},{"addr":"0x6dc880","name":"nullsub_616","size":"0x1","has_type":false},{"addr":"0x6dc8a0","name":"sub_6DC8A0","size":"0x4","has_type":false},{"addr":"0x6dc930","name":"sub_6DC930","size":"0x61","has_type":false},{"addr":"0x6dc9a0","name":"sub_6DC9A0","size":"0x22","has_type":false},{"addr":"0x6dc9d0","name":"sub_6DC9D0","size":"0x6","has_type":true},{"addr":"0x6dca00","name":"sub_6DCA00","size":"0x185","has_type":false},{"addr":"0x6dcb90","name":"sub_6DCB90","size":"0x5","has_type":false},{"addr":"0x6dcba0","name":"sub_6DCBA0","size":"0x37","has_type":false},{"addr":"0x6dce80","name":"sub_6DCE80","size":"0x66","has_type":true},{"addr":"0x6dcef0","name":"sub_6DCEF0","size":"0x8c","has_type":false},{"addr":"0x6dcf80","name":"sub_6DCF80","size":"0x157","has_type":false},{"addr":"0x6dd110","name":"sub_6DD110","size":"0x1e4","has_type":false},{"addr":"0x6dd330","name":"sub_6DD330","size":"0x2d","has_type":true},{"addr":"0x6dd360","name":"sub_6DD360","size":"0x177","has_type":false},{"addr":"0x6dd4e0","name":"sub_6DD4E0","size":"0xc8","has_type":false},{"addr":"0x6dd5e0","name":"sub_6DD5E0","size":"0xbc","has_type":false},{"addr":"0x6dd6d0","name":"sub_6DD6D0","size":"0x206","has_type":true},{"addr":"0x6dd980","name":"sub_6DD980","size":"0x4","has_type":false},{"addr":"0x6ddd20","name":"sub_6DDD20","size":"0x83","has_type":false},{"addr":"0x6dddb0","name":"sub_6DDDB0","size":"0xda","has_type":false},{"addr":"0x6dde90","name":"sub_6DDE90","size":"0xfa","has_type":true},{"addr":"0x6ddfe0","name":"sub_6DDFE0","size":"0x1b","has_type":false},{"addr":"0x6de000","name":"sub_6DE000","size":"0x4f","has_type":false},{"addr":"0x6de070","name":"sub_6DE070","size":"0x5d","has_type":false},{"addr":"0x6de0d0","name":"sub_6DE0D0","size":"0x2d","has_type":false},{"addr":"0x6de100","name":"sub_6DE100","size":"0x3a","has_type":false},{"addr":"0x6de140","name":"sub_6DE140","size":"0x168","has_type":true},{"addr":"0x6de2f0","name":"??0_ReaderWriterLock@details@Concurrency@@QAE@XZ_177","size":"0x10","has_type":false},{"addr":"0x6de300","name":"sub_6DE300","size":"0x77","has_type":false},{"addr":"0x6de380","name":"sub_6DE380","size":"0x6c","has_type":false},{"addr":"0x6de3f0","name":"sub_6DE3F0","size":"0xa5","has_type":false},{"addr":"0x6de500","name":"sub_6DE500","size":"0x50","has_type":false},{"addr":"0x6de550","name":"sub_6DE550","size":"0xa3","has_type":false},{"addr":"0x6de660","name":"sub_6DE660","size":"0x63","has_type":false},{"addr":"0x6de750","name":"__RTC_NumErrors_789","size":"0x6","has_type":true},{"addr":"0x6de850","name":"sub_6DE850","size":"0x133","has_type":false},{"addr":"0x6de990","name":"sub_6DE990","size":"0x99","has_type":false},{"addr":"0x6dea30","name":"sub_6DEA30","size":"0x4","has_type":false},{"addr":"0x6dea60","name":"sub_6DEA60","size":"0x4","has_type":false},{"addr":"0x6dea70","name":"sub_6DEA70","size":"0x72","has_type":true},{"addr":"0x6deb20","name":"sub_6DEB20","size":"0xe","has_type":true},{"addr":"0x6deb30","name":"sub_6DEB30","size":"0x4","has_type":false},{"addr":"0x6deb90","name":"sub_6DEB90","size":"0x86","has_type":false},{"addr":"0x6dec30","name":"?clear@?$vector@PAXV?$allocator@PAX@std@@@std@@QAEXXZ_4","size":"0x7","has_type":false},{"addr":"0x6decc0","name":"sub_6DECC0","size":"0x8f","has_type":false},{"addr":"0x6ded50","name":"sub_6DED50","size":"0x6d","has_type":false},{"addr":"0x6dedc0","name":"sub_6DEDC0","size":"0x10","has_type":false},{"addr":"0x6dee70","name":"sub_6DEE70","size":"0xb","has_type":false},{"addr":"0x6def00","name":"sub_6DEF00","size":"0x44","has_type":false},{"addr":"0x6def80","name":"sub_6DEF80","size":"0x7f","has_type":false},{"addr":"0x6df020","name":"sub_6DF020","size":"0x68","has_type":false},{"addr":"0x6df090","name":"sub_6DF090","size":"0x68","has_type":false},{"addr":"0x6df1b0","name":"sub_6DF1B0","size":"0x53","has_type":false},{"addr":"0x6df210","name":"sub_6DF210","size":"0x77","has_type":false},{"addr":"0x6df290","name":"sub_6DF290","size":"0x77","has_type":false},{"addr":"0x6df310","name":"nullsub_617","size":"0x1","has_type":false},{"addr":"0x6df320","name":"nullsub_618","size":"0x1","has_type":false},{"addr":"0x6df340","name":"sub_6DF340","size":"0x4","has_type":false},{"addr":"0x6df3f0","name":"sub_6DF3F0","size":"0x5","has_type":false},{"addr":"0x6df440","name":"sub_6DF440","size":"0x4","has_type":false},{"addr":"0x6df450","name":"sub_6DF450","size":"0x4","has_type":false},{"addr":"0x6df460","name":"sub_6DF460","size":"0x4","has_type":false},{"addr":"0x6df470","name":"sub_6DF470","size":"0x79","has_type":false},{"addr":"0x6df4f0","name":"sub_6DF4F0","size":"0xf","has_type":true},{"addr":"0x6df500","name":"Phyre_LoadCharacterBtmToTopShader","size":"0x93","has_type":true},{"addr":"0x6df5a0","name":"Phyre_LoadMagicFile249Shader","size":"0x93","has_type":true},{"addr":"0x6df640","name":"Phyre_LoadMagicFile297Shader","size":"0x93","has_type":true},{"addr":"0x6df750","name":"sub_6DF750","size":"0xa4","has_type":false},{"addr":"0x6df800","name":"sub_6DF800","size":"0x1ef","has_type":false},{"addr":"0x6df9f0","name":"sub_6DF9F0","size":"0x85","has_type":true},{"addr":"0x6dfa80","name":"sub_6DFA80","size":"0xdf","has_type":false},{"addr":"0x6dfb60","name":"sub_6DFB60","size":"0xa0","has_type":false},{"addr":"0x6dfc00","name":"sub_6DFC00","size":"0x2f7","has_type":false},{"addr":"0x6dff00","name":"sub_6DFF00","size":"0x85","has_type":false},{"addr":"0x6e0020","name":"sub_6E0020","size":"0x3b","has_type":false},{"addr":"0x6e0090","name":"__RTC_NumErrors_790","size":"0x6","has_type":true},{"addr":"0x6e00a0","name":"__RTC_NumErrors_791","size":"0x6","has_type":true},{"addr":"0x6e00b0","name":"__RTC_NumErrors_792","size":"0x6","has_type":true},{"addr":"0x6e00c0","name":"sub_6E00C0","size":"0x6","has_type":false},{"addr":"0x6e00d0","name":"sub_6E00D0","size":"0x6","has_type":false},{"addr":"0x6e00e0","name":"sub_6E00E0","size":"0x6","has_type":false},{"addr":"0x6e0230","name":"sub_6E0230","size":"0x6","has_type":false},{"addr":"0x6e0240","name":"sub_6E0240","size":"0x6","has_type":false},{"addr":"0x6e0250","name":"sub_6E0250","size":"0x6","has_type":false},{"addr":"0x6e05d0","name":"sub_6E05D0","size":"0x77","has_type":false},{"addr":"0x6e0650","name":"??0_ReaderWriterLock@details@Concurrency@@QAE@XZ_178","size":"0x10","has_type":false}]